redshift_connector_bade/__init__.py
redshift_connector_bade/connector.py
redshift_connector_bade-0.1.3.dist-info/licenses/LICENSE
redshift_connector_bade-0.1.3.dist-info/METADATA
redshift_connector_bade-0.1.3.dist-info/WHEEL
redshift_connector_bade-0.1.3.dist-info/top_level.txt
redshift_connector_bade-0.1.3.dist-info/RECORD
