Metadata-Version: 2.4
Name: redshift-connector-bade
Version: 0.1.3
Summary: A simple connector for Amazon Redshift using JDBC
Home-page: https://github.com/royhsu1012/redshift_connector
Author: Hans, Roy
Author-email: royhsu1012@hmail.com
Classifier: Programming Language :: Python :: 3
Classifier: License :: OSI Approved :: MIT License
Classifier: Operating System :: OS Independent
Requires-Python: >=3.6
License-File: LICENSE
Requires-Dist: jpype1
Requires-Dist: jaydebeapi
Requires-Dist: pandas
Requires-Dist: requests
Dynamic: author
Dynamic: author-email
Dynamic: classifier
Dynamic: description
Dynamic: description-content-type
Dynamic: home-page
Dynamic: license-file
Dynamic: requires-dist
Dynamic: requires-python
Dynamic: summary
